ecubevis/__init__.py
ecubevis/ecubevis.py
ecubevis/io.py
ecubevis/mpl_helpfunc.py
ecubevis/utils.py
ecubevis-1.0.2.dist-info/LICENSE
ecubevis-1.0.2.dist-info/METADATA
ecubevis-1.0.2.dist-info/WHEEL
ecubevis-1.0.2.dist-info/top_level.txt
ecubevis-1.0.2.dist-info/RECORD
