Metadata-Version: 2.1
Name: ecubevis
Version: 1.0.2
Summary: Earth CUBE VISualization with Python
Home-page: https://github.com/carlgogo/ecubevis
Author: Carlos Alberto Gomez Gonzalez
Author-email: carlos.gomez@bsc.es
License: Apache v2.0
Keywords: visualization,interactive,plotting,earth-data
Classifier: Intended Audience :: Science/Research
Classifier: Operating System :: POSIX :: Linux
Classifier: Natural Language :: English
Classifier: License :: OSI Approved :: Apache Software License
Classifier: Programming Language :: Python
Classifier: Programming Language :: Python :: 3
Classifier: Programming Language :: Python :: 3.7
Classifier: Topic :: Scientific/Engineering
Classifier: Topic :: Scientific/Engineering :: Visualization
License-File: LICENSE
Requires-Dist: numpy
Requires-Dist: matplotlib
Requires-Dist: xarray
Requires-Dist: hvplot
Requires-Dist: holoviews
Requires-Dist: pyproj
Requires-Dist: cartopy
Requires-Dist: geoviews
Requires-Dist: bokeh
Requires-Dist: pyviz-comms
Requires-Dist: joblib
Requires-Dist: netcdf4
